[
    {
        "pregunta": "1. \u00bfCu\u00e1l es el oc\u00e9ano m\u00e1s grande del mundo?",
        "respuesta": "Oc\u00e9ano Pac\u00edfico.",
        "peso": 0
    },
    {
        "pregunta": "2. \u00bfCu\u00e1l es la capa superior del oc\u00e9ano donde hay luz?",
        "respuesta": "Zona f\u00f3tica.",
        "peso": 0
    },
    {
        "pregunta": "3. \u00bfQu\u00e9 es un arrecife de coral?",
        "respuesta": "Una estructura marina formada por corales.",
        "peso": 0
    },
    {
        "pregunta": "4. \u00bfCu\u00e1l es el mam\u00edfero m\u00e1s grande del oc\u00e9ano?",
        "respuesta": "La ballena azul.",
        "peso": 0
    },
    {
        "pregunta": "5. \u00bfQu\u00e9 porcentaje de la superficie de la Tierra est\u00e1 cubierta por oc\u00e9anos?",
        "respuesta": "Aproximadamente 71%.",
        "peso": 0
    },
    {
        "pregunta": "6. \u00bfQu\u00e9 es el plancton?",
        "respuesta": "Peque\u00f1os organismos que flotan en el oc\u00e9ano y sirven de alimento.",
        "peso": 0
    },
    {
        "pregunta": "7. \u00bfCu\u00e1l es el oc\u00e9ano m\u00e1s peque\u00f1o del mundo?",
        "respuesta": "Oc\u00e9ano \u00c1rtico.",
        "peso": 0
    },
    {
        "pregunta": "8. \u00bfQu\u00e9 es la marea?",
        "respuesta": "La subida y bajada del nivel del mar causada por la gravedad de la Luna y el Sol.",
        "peso": 0
    },
    {
        "pregunta": "9. \u00bfQu\u00e9 causa las olas en el oc\u00e9ano?",
        "respuesta": "Principalmente el viento.",
        "peso": 0
    },
    {
        "pregunta": "10. \u00bfQu\u00e9 es una corriente oce\u00e1nica?",
        "respuesta": "Un flujo continuo de agua en el oc\u00e9ano, como la Corriente del Golfo.",
        "peso": 0
    },
    {
        "pregunta": "11. \u00bfQu\u00e9 es una especie de pez bioluminiscente?",
        "respuesta": "El pez linterna.",
        "peso": 0
    },
    {
        "pregunta": "12. \u00bfQu\u00e9 tipo de agua hay en el oc\u00e9ano?",
        "respuesta": "Agua salada.",
        "peso": 0
    },
    {
        "pregunta": "13. \u00bfQu\u00e9 son las algas marinas?",
        "respuesta": "Plantas y organismos marinos que producen ox\u00edgeno y sirven de alimento.",
        "peso": 0
    },
    {
        "pregunta": "14. \u00bfQu\u00e9 es una trinchera oce\u00e1nica?",
        "respuesta": "Una profunda depresi\u00f3n en el suelo oce\u00e1nico.",
        "peso": 0
    },
    {
        "pregunta": "15. \u00bfQu\u00e9 es el mar de los Sargazos?",
        "respuesta": "Una regi\u00f3n en el Atl\u00e1ntico Norte llena de algas sargazo.",
        "peso": 0
    },
    {
        "pregunta": "16. \u00bfCu\u00e1l es el mayor arrecife de coral del mundo?",
        "respuesta": "La Gran Barrera de Coral.",
        "peso": 0
    },
    {
        "pregunta": "17. \u00bfQu\u00e9 es la Zona Abisal?",
        "respuesta": "La parte profunda y oscura del oc\u00e9ano.",
        "peso": 0
    },
    {
        "pregunta": "18. \u00bfQu\u00e9 es la zona de afloramiento en el oc\u00e9ano?",
        "respuesta": "Un \u00e1rea donde aguas profundas y ricas en nutrientes ascienden a la superficie.",
        "peso": 0
    },
    {
        "pregunta": "19. \u00bfCu\u00e1l es el nombre de la corriente c\u00e1lida que afecta el clima en Europa?",
        "respuesta": "La Corriente del Golfo.",
        "peso": 0
    },
    {
        "pregunta": "20. \u00bfQu\u00e9 es el fitoplancton?",
        "respuesta": "Plantas microsc\u00f3picas que flotan y producen ox\u00edgeno.",
        "peso": 0
    },
    {
        "pregunta": "21. \u00bfCu\u00e1l es el punto m\u00e1s profundo del oc\u00e9ano?",
        "respuesta": "La Fosa de las Marianas.",
        "peso": 0
    },
    {
        "pregunta": "22. \u00bfQu\u00e9 fen\u00f3meno clim\u00e1tico se origina en el oc\u00e9ano y afecta globalmente?",
        "respuesta": "El Ni\u00f1o.",
        "peso": 0
    },
    {
        "pregunta": "23. \u00bfC\u00f3mo afecta la salinidad a la densidad del agua oce\u00e1nica?",
        "respuesta": "A mayor salinidad, mayor densidad.",
        "peso": 0
    },
    {
        "pregunta": "24. \u00bfQu\u00e9 animal es conocido por su capacidad de cambiar de color en el oc\u00e9ano?",
        "respuesta": "El pulpo.",
        "peso": 0
    },
    {
        "pregunta": "25. \u00bfQu\u00e9 es el oc\u00e9ano abisal?",
        "respuesta": "La capa m\u00e1s profunda y oscura del oc\u00e9ano.",
        "peso": 0
    },
    {
        "pregunta": "26. \u00bfQu\u00e9 es la acidificaci\u00f3n del oc\u00e9ano?",
        "respuesta": "El aumento de acidez en el agua marina debido a la absorci\u00f3n de CO\u2082.",
        "peso": 0
    },
    {
        "pregunta": "27. \u00bfQu\u00e9 son las fumarolas hidrotermales?",
        "respuesta": "Grietas en el fondo del oc\u00e9ano que emiten agua caliente rica en minerales.",
        "peso": 0
    },
    {
        "pregunta": "28. \u00bfQu\u00e9 es el zooplancton?",
        "respuesta": "Organismos animales microsc\u00f3picos que flotan en el oc\u00e9ano.",
        "peso": 0
    },
    {
        "pregunta": "29. \u00bfCu\u00e1l es la principal causa de las mareas vivas?",
        "respuesta": "La alineaci\u00f3n de la Tierra, la Luna y el Sol.",
        "peso": 0
    },
    {
        "pregunta": "30. \u00bfQu\u00e9 es el 'Gran Parche de Basura del Pac\u00edfico'?",
        "respuesta": "Una gran acumulaci\u00f3n de basura flotante en el Oc\u00e9ano Pac\u00edfico.",
        "peso": 0
    },
    {
        "pregunta": "31. \u00bfQu\u00e9 es el mar profundo?",
        "respuesta": "Regiones oce\u00e1nicas a gran profundidad sin luz solar.",
        "peso": 0
    },
    {
        "pregunta": "32. \u00bfQu\u00e9 es la Zona Hadal?",
        "respuesta": "Las \u00e1reas m\u00e1s profundas del oc\u00e9ano, como las fosas oce\u00e1nicas.",
        "peso": 0
    }
]